djangordf/__init__.py
djangordf/functions.py
djangordf-0.1.1.dist-info/LICENSE
djangordf-0.1.1.dist-info/METADATA
djangordf-0.1.1.dist-info/WHEEL
djangordf-0.1.1.dist-info/top_level.txt
djangordf-0.1.1.dist-info/RECORD
