Metadata-Version: 2.1
Name: djangordf
Version: 0.1.1
Summary: A RDF library for Django models
Home-page: https://github.com/judaicalink/djangordf
Author: Benjamin Schnabel
Classifier: Programming Language :: Python :: 3
Classifier: License :: OSI Approved :: MIT License
Classifier: Operating System :: OS Independent
Requires-Python: >=3.6
License-File: LICENSE
